fdp/Sections.py
fdp/__init__.py
flexible_data_parser-1.0.dist-info/DESCRIPTION.rst
flexible_data_parser-1.0.dist-info/METADATA
flexible_data_parser-1.0.dist-info/RECORD
flexible_data_parser-1.0.dist-info/WHEEL
flexible_data_parser-1.0.dist-info/metadata.json
flexible_data_parser-1.0.dist-info/top_level.txt
