Metadata-Version: 2.0
Name: flexible-data-parser
Version: 1.0
Summary: A configurable semi-structured data parser
Home-page: https://github.com/glitchassassin/flexible-data-parser
Author: Jon Winsley
Author-email: jon.winsley@gmail.com
License: MIT
Keywords: data parse
Platform: UNKNOWN
Classifier: Development Status :: 5 - Production/Stable
Classifier: Intended Audience :: Developers
Classifier: Intended Audience :: Healthcare Industry
Classifier: License :: OSI Approved :: MIT License
Classifier: Operating System :: OS Independent
